README.txt
bootstrap.py
buildout.cfg
setup.py
Products/__init__.py
Products.JRedirector.egg-info/PKG-INFO
Products.JRedirector.egg-info/SOURCES.txt
Products.JRedirector.egg-info/dependency_links.txt
Products.JRedirector.egg-info/entry_points.txt
Products.JRedirector.egg-info/namespace_packages.txt
Products.JRedirector.egg-info/not-zip-safe
Products.JRedirector.egg-info/requires.txt
Products.JRedirector.egg-info/top_level.txt
Products/JRedirector/CHANGES.txt
Products/JRedirector/COPYRIGHT.txt
Products/JRedirector/JRedirector.py
Products/JRedirector/LICENSE.txt
Products/JRedirector/README.txt
Products/JRedirector/VERSION.txt
Products/JRedirector/__init__.py
Products/JRedirector/interfaces.py
Products/JRedirector/dtml/add.dtml
Products/JRedirector/dtml/log.dtml
Products/JRedirector/dtml/mappings.dtml
Products/JRedirector/dtml/settings.dtml
Products/JRedirector/help/Add.stx
Products/JRedirector/help/Log.stx
Products/JRedirector/help/Mappings.stx
Products/JRedirector/help/Properties.stx
Products/JRedirector/www/jredirector.gif