Metadata-Version: 1.0
Name: Products.JRedirector
Version: 1.4
Summary: Simple Zope 2 redirection manager object
Home-page: http://pypi.python.org/pypi/Products.JRedirector
Author: Jens Vagelpohl
Author-email: jens@dataflake.org
License: ZPL 2.1 (http://www.zope.org/Resources/License/ZPL-2.1)
Keywords: web zope zope2 redirector
Platform: UNKNOWN
Classifier: Development Status :: 5 - Production/Stable
Classifier: Framework :: Zope2
Classifier: Intended Audience :: Developers
Classifier: License :: OSI Approved :: Zope Public License
Classifier: Programming Language :: Python
Classifier: Topic :: Internet :: WWW/HTTP :: Site Management
Classifier: Topic :: Software Development
Classifier: Topic :: Software Development :: Libraries :: Python Modules
